x27cn/__init__.py
x27cn/advanced.py
x27cn/anti_crawl.py
x27cn/cli.py
x27cn/core.py
x27cn/minify.py
x27cn/obfuscate.py
x27cn/password.py
x27cn-1.4.3.dist-info/licenses/LICENSE
x27cn-1.4.3.dist-info/METADATA
x27cn-1.4.3.dist-info/WHEEL
x27cn-1.4.3.dist-info/entry_points.txt
x27cn-1.4.3.dist-info/top_level.txt
x27cn-1.4.3.dist-info/RECORD
