Metadata-Version: 2.4
Name: x27cn
Version: 1.4.3
Summary: X27CN - Advanced code obfuscation, encryption and anti-crawl protection
Author-email: CFspider <cfspider@example.com>
License-Expression: MIT
Project-URL: Homepage, https://github.com/violettoolssite/CFspider
Project-URL: Documentation, https://github.com/violettoolssite/CFspider#x27cn-加密库
Project-URL: Repository, https://github.com/violettoolssite/CFspider
Project-URL: Issues, https://github.com/violettoolssite/CFspider/issues
Keywords: encryption,obfuscation,security,encoding,html,javascript,anti-debug,anti-crawl,code-protection
Classifier: Development Status :: 4 - Beta
Classifier: Intended Audience :: Developers
Classifier: Operating System :: OS Independent
Classifier: Programming Language :: Python :: 3
Classifier: Programming Language :: Python :: 3.7
Classifier: Programming Language :: Python :: 3.8
Classifier: Programming Language :: Python :: 3.9
Classifier: Programming Language :: Python :: 3.10
Classifier: Programming Language :: Python :: 3.11
Classifier: Programming Language :: Python :: 3.12
Classifier: Topic :: Security :: Cryptography
Classifier: Topic :: Software Development :: Libraries :: Python Modules
Requires-Python: >=3.7
License-File: LICENSE
Dynamic: license-file
